colorfan.py
Colorfan-0.1.0.dist-info/METADATA
Colorfan-0.1.0.dist-info/WHEEL
Colorfan-0.1.0.dist-info/top_level.txt
Colorfan-0.1.0.dist-info/RECORD
