Metadata-Version: 2.1
Name: Colorfan
Version: 0.1.0
Summary: A powerful python module to set console color
Home-page: https://github.com/hushra/colorfan
Author: Hamidreza Ahmadi
Author-email: your.email@example.com
Classifier: License :: OSI Approved :: MIT License
Classifier: Programming Language :: Python :: 3
Classifier: Programming Language :: Python :: 3.6
Classifier: Programming Language :: Python :: 3.7
Classifier: Programming Language :: Python :: 3.8
Classifier: Programming Language :: Python :: 3.9
Classifier: Programming Language :: Python :: Implementation :: CPython
Classifier: Programming Language :: Python :: Implementation :: PyPy
